Workbook
Name anos: Planilha1!$D$23
Name patrimonio_acumulado: Planilha1!$D$26
Name perfil: Planilha1!$E$37
Name rendimento_carteira: Planilha1!$E$18
Name salario: Planilha1!$E$17
Name taxa_mensal: Planilha1!$D$25
Name valor_investir: Planilha1!$D$22

Sheet Planilha1
C16: Configurações | H16: Calculo Bola de Neve
C17: Salário | E17: 2500 | H17: Preço Médio da Cota | J17: 10
C18: Rendimento Carteira | E18: 0.006 | H18: Patrimônio Necessário | J18: =J17/taxa_mensal -> 926.78406
C19: Sujestão Investimento | E19: =E17*30% -> 750 | H19: Cotas Necessárias | J19: =J18/J17 -> 92.678406
C21: Parâmetros de Simulção | H21: Meta de Renda Mensal
C22: Quanto Investir por mês? | D22: 600 | H22: Quero Receber? | J22: 3000
C23: Por Quantos Anos? | D23: 5 | H23: Patrimônio Necessário | J23: =J22/taxa_mensal -> 278035.22
C24: Inflação Anual Estimada (IPCA) | D24: 0.05 | H24: Tempo Estimado (anos) | J24: =NPER(taxa_mensal,-valor_investir,0,J23)/12 -> 13.912641
C25: Taxa de Rendimento Mensal? | D25: 0.01079
C26: Patrimõnio Acumulado? | D26: =FV(taxa_mensal,anos*12,valor_investir*-1) -> 50266.148
C27: Dividendo Mensais? | D27: =patrimonio_acumulado*rendimento_carteira -> 301.59689
C29: Cenários | D29: Saldo Nominal | F29: Poder de Compra | G29: Dividendo
B30: 2 | C30: Quanto em 2 Anos? | D30: =FV($D$25,$B30*12,$D$22*-1) -> 16336.576 | F30: =FV( ((1+taxa_mensal)/((1+$D$24)^(1/12)))-1, $B30*12, valor_investir * - 1 ) -> 15563.926 | G30: =$D30*rendimento_carteira -> 98.019458
B31: 5 | C31: Quanto em 5 Anos? | D31: =FV($D$25,$B31*12,$D$22*-1) -> 50266.148 | F31: =FV( ((1+taxa_mensal)/((1+$D$24)^(1/12)))-1, $B31*12, valor_investir * - 1 ) -> 44116.408 | G31: =$D31*rendimento_carteira -> 301.59689
B32: 10 | C32: Quanto em 10 Anos? | D32: =FV($D$25,$B32*12,$D$22*-1) -> 145970.53 | F32: =FV( ((1+taxa_mensal)/((1+$D$24)^(1/12)))-1, $B32*12, valor_investir * - 1 ) -> 109929.13 | G32: =$D32*rendimento_carteira -> 875.82317
B33: 20 | C33: Quanto em 20 Anos? | D33: =FV($D$25,$B33*12,$D$22*-1) -> 675119.04 | F33: =FV( ((1+taxa_mensal)/((1+$D$24)^(1/12)))-1, $B33*12, valor_investir * - 1 ) -> 354571.8 | G33: =$D33*rendimento_carteira -> 4050.7142
B34: 30 | C34: Quanto em 30 Anos? | D34: =FV($D$25,$B34*12,$D$22*-1) -> 2593301.8 | F34: =FV( ((1+taxa_mensal)/((1+$D$24)^(1/12)))-1, $B34*12, valor_investir * - 1 ) -> 899013.79 | G34: =$D34*rendimento_carteira -> 15559.811
C37: PERFIL | E37: CONSERVADOR
C38: VALOR A SER INVESTIDO POR MÊS | E38: =valor_investir -> 600
C40: TIPO DE FII | D40: Percentual Sugerido | E40: Valores
C41: PAPEL | D41: =VLOOKUP(perfil&"-"&$C41,Planilha2!$B:$E,4,FALSE) -> 0.3 | E41: =$D41*$E$38 -> 180
C42: TIJOLO | D42: =VLOOKUP(perfil&"-"&$C42,Planilha2!$B:$E,4,FALSE) -> 0.5 | E42: =$D42*$E$38 -> 300
C43: HÍBRIDOS | D43: =VLOOKUP(perfil&"-"&$C43,Planilha2!$B:$E,4,FALSE) -> 0.1 | E43: =$D43*$E$38 -> 60
C44: FOFs | D44: =VLOOKUP(perfil&"-"&$C44,Planilha2!$B:$E,4,FALSE) -> 0.1 | E44: =$D44*$E$38 -> 60
C45: DESENVOLVIMENTO | D45: =VLOOKUP(perfil&"-"&$C45,Planilha2!$B:$E,4,FALSE) -> 0 | E45: =$D45*$E$38 -> 0
C46: HOTELARIAS | D46: =VLOOKUP(perfil&"-"&$C46,Planilha2!$B:$E,4,FALSE) -> 0 | E46: =$D46*$E$38 -> 0
E47: =SUM(E41:E46) -> 600

Sheet Planilha2
B3: chave | C3: PERFIL | D3: TIPO DE FII | E3: %
B4: =$C$4&"-"&D4 -> CONSERVADOR-PAPEL | C4: CONSERVADOR | D4: PAPEL | E4: 0.3
B5: =$C$4&"-"&D5 -> CONSERVADOR-TIJOLO | C5: CONSERVADOR | D5: TIJOLO | E5: 0.5
B6: =$C$4&"-"&D6 -> CONSERVADOR-HÍBRIDOS | C6: CONSERVADOR | D6: HÍBRIDOS | E6: 0.1
B7: =$C$4&"-"&D7 -> CONSERVADOR-FOFs | C7: CONSERVADOR | D7: FOFs | E7: 0.1
B8: =$C$4&"-"&D8 -> CONSERVADOR-DESENVOLVIMENTO | C8: CONSERVADOR | D8: DESENVOLVIMENTO | E8: 0
B9: =$C$4&"-"&D9 -> CONSERVADOR-HOTELARIAS | C9: CONSERVADOR | D9: HOTELARIAS | E9: 0
B10: =$C$10&"-"&D10 -> MODERADO-PAPEL | C10: MODERADO | D10: PAPEL | E10: 0.32
B11: =$C$10&"-"&D11 -> MODERADO-TIJOLO | C11: MODERADO | D11: TIJOLO | E11: 0.35
B12: =$C$10&"-"&D12 -> MODERADO-HÍBRIDOS | C12: MODERADO | D12: HÍBRIDOS | E12: 0.08
B13: =$C$10&"-"&D13 -> MODERADO-FOFs | C13: MODERADO | D13: FOFs | E13: 0.05
B14: =$C$10&"-"&D14 -> MODERADO-DESENVOLVIMENTO | C14: MODERADO | D14: DESENVOLVIMENTO | E14: 0.1
B15: =$C$10&"-"&D15 -> MODERADO-HOTELARIAS | C15: MODERADO | D15: HOTELARIAS | E15: 0.1
B16: =$C$16&"-"&D16 -> AGRESSIVO-PAPEL | C16: AGRESSIVO | D16: PAPEL | E16: 0.5
B17: =$C$16&"-"&D17 -> AGRESSIVO-TIJOLO | C17: AGRESSIVO | D17: TIJOLO | E17: 0.1
B18: =$C$16&"-"&D18 -> AGRESSIVO-HÍBRIDOS | C18: AGRESSIVO | D18: HÍBRIDOS | E18: 0.05
B19: =$C$16&"-"&D19 -> AGRESSIVO-FOFs | C19: AGRESSIVO | D19: FOFs | E19: 0.05
B20: =$C$16&"-"&D20 -> AGRESSIVO-DESENVOLVIMENTO | C20: AGRESSIVO | D20: DESENVOLVIMENTO | E20: 0.2
B21: =$C$16&"-"&D21 -> AGRESSIVO-HOTELARIAS | C21: AGRESSIVO | D21: HOTELARIAS | E21: 0.1
